{
  "name": "Fearow",
  "dex": 22,
  "generation": 1,
  "types": [
    "normal",
    "flying"
  ],
  "baseStats": {
    "stamina": 130,
    "attack": 182,
    "defense": 135
  },
  "previousEvolution": "POKEMON_SPEAROW",
  "nextEvolutions": [],
  "quickMoves": [
    {
      "id": "MOVE_PECK_FAST",
      "legacy": false
    },
    {
      "id": "MOVE_STEEL_WING_FAST",
      "legacy": false
    }
  ],
  "chargeMoves": [
    {
      "id": "MOVE_AERIAL_ACE",
      "legacy": false
    },
    {
      "id": "MOVE_DRILL_RUN",
      "legacy": false
    },
    {
      "id": "MOVE_SKY_ATTACK",
      "legacy": false
    }
  ],
  "rarity": null,
  "buddyDistance": 0.25,
  "height": 1.2,
  "weight": 38,
  "family": "FAMILY_SPEAROW",
  "forms": null,
  "_id": "POKEMON_FEAROW"
}