{
  "name": "Charmander",
  "dex": 4,
  "generation": 1,
  "types": [
    "fire"
  ],
  "baseStats": {
    "stamina": 78,
    "attack": 116,
    "defense": 96
  },
  "previousEvolution": null,
  "nextEvolutions": [
    {
      "pokemon": "POKEMON_CHARMELEON",
      "candy": 25,
      "item": null
    }
  ],
  "quickMoves": [
    "MOVE_EMBER_FAST",
    "MOVE_SCRATCH_FAST"
  ],
  "chargeMoves": [
    "MOVE_FLAME_CHARGE",
    "MOVE_FLAME_BURST",
    "MOVE_FLAMETHROWER"
  ],
  "rarity": null,
  "maxCP": 831,
  "buddyDistance": 3,
  "height": 0.6,
  "weight": 8.5,
  "_id": "POKEMON_CHARMANDER"
}