{
  "name": "Cubone",
  "dex": 104,
  "generation": 1,
  "types": [
    "ground"
  ],
  "baseStats": {
    "stamina": 100,
    "attack": 90,
    "defense": 165
  },
  "previousEvolution": null,
  "nextEvolutions": [
    {
      "pokemon": "POKEMON_MAROWAK",
      "candy": 50,
      "item": null
    }
  ],
  "quickMoves": [
    {
      "id": "MOVE_MUD_SLAP_FAST",
      "legacy": false
    },
    {
      "id": "MOVE_ROCK_SMASH_FAST",
      "legacy": false
    }
  ],
  "chargeMoves": [
    {
      "id": "MOVE_BONE_CLUB",
      "legacy": false
    },
    {
      "id": "MOVE_DIG",
      "legacy": false
    },
    {
      "id": "MOVE_BULLDOZE",
      "legacy": false
    }
  ],
  "rarity": null,
  "maxCP": 943,
  "buddyDistance": 3,
  "height": 0.4,
  "weight": 6.5,
  "family": {
    "id": "FAMILY_CUBONE"
  },
  "_id": "POKEMON_CUBONE"
}