{
  "baseStats": {
    "attack": 131,
    "defense": 128,
    "stamina": 225
  },
  "buddyDistance": 3,
  "chargeMoves": {
    "MOVE_DIG": false,
    "MOVE_DRILL_RUN": false,
    "MOVE_ROCK_SLIDE": false
  },
  "dex": 206,
  "family": "FAMILY_DUNSPARCE",
  "generation": 2,
  "height": 1.5,
  "name": "Dunsparce",
  "nextEvolutions": [
  ],
  "previousEvolution": null,
  "quickMoves": {
    "MOVE_ASTONISH_FAST": false,
    "MOVE_BITE_FAST": false
  },
  "rarity": "common",
  "types": [
    "normal"
  ],
  "weight": 14
}