{
  "name": "Electrike",
  "dex": 309,
  "family": "FAMILY_ELECTRIKE",
  "generation": 3,
  "types": [
    "electric"
  ],
  "baseStats": {
    "stamina": 80,
    "attack": 123,
    "defense": 78
  },
  "previousEvolution": null,
  "nextEvolutions": [
    {
      "pokemon": "POKEMON_MANECTRIC",
      "candy": 50
    }
  ],
  "quickMoves": {
    "MOVE_SPLASH_FAST": true,
    "MOVE_QUICK_ATTACK_FAST": false,
    "MOVE_SPARK_FAST": false
  },
  "chargeMoves": {
    "MOVE_STRUGGLE": true,
    "MOVE_THUNDERBOLT": false,
    "MOVE_DISCHARGE": false,
    "MOVE_SWIFT": false
  },
  "rarity": null,
  "buddyDistance": 3,
  "height": 0.61,
  "weight": 15.2
}
