{
  "name": "Forretress",
  "dex": 205,
  "generation": 2,
  "types": [
    "bug",
    "steel"
  ],
  "baseStats": {
    "stamina": 150,
    "attack": 161,
    "defense": 242
  },
  "previousEvolution": "POKEMON_PINECO",
  "nextEvolutions": [],
  "quickMoves": [
    {
      "id": "MOVE_BUG_BITE_FAST",
      "legacy": false
    },
    {
      "id": "MOVE_STRUGGLE_BUG_FAST",
      "legacy": false
    }
  ],
  "chargeMoves": [
    {
      "id": "MOVE_HEAVY_SLAM",
      "legacy": false
    },
    {
      "id": "MOVE_EARTHQUAKE",
      "legacy": false
    },
    {
      "id": "MOVE_ROCK_TOMB",
      "legacy": false
    }
  ],
  "rarity": null,
  "buddyDistance": 5,
  "height": 1.19,
  "weight": 125.8,
  "family": "FAMILY_PINECO",
  "forms": null,
  "_id": "POKEMON_FORRETRESS"
}