{
  "name": "Girafarig",
  "dex": 203,
  "generation": 2,
  "types": [
    "normal",
    "psychic"
  ],
  "baseStats": {
    "stamina": 140,
    "attack": 182,
    "defense": 133
  },
  "previousEvolution": null,
  "nextEvolutions": [],
  "quickMoves": [
    {
      "id": "MOVE_TACKLE_FAST",
      "legacy": false
    },
    {
      "id": "MOVE_CONFUSION_FAST",
      "legacy": false
    }
  ],
  "chargeMoves": [
    {
      "id": "MOVE_PSYCHIC",
      "legacy": false
    },
    {
      "id": "MOVE_THUNDERBOLT",
      "legacy": false
    },
    {
      "id": "MOVE_MIRROR_COAT",
      "legacy": false
    }
  ],
  "rarity": null,
  "maxCP": 1863,
  "buddyDistance": 0.75,
  "height": 1.5,
  "weight": 41.5,
  "family": "FAMILY_GIRAFARIG",
  "forms": null,
  "_id": "POKEMON_GIRAFARIG"
}