{
  "name": "Beautifly",
  "dex": 267,
  "generation": 3,
  "types": [
    "bug",
    "flying"
  ],
  "baseStats": {
    "stamina": 120,
    "attack": 189,
    "defense": 98
  },
  "previousEvolution": "POKEMON_SILCOON",
  "nextEvolutions": [],
  "quickMoves": [
    {
      "id": "MOVE_SPLASH_FAST",
      "legacy": true
    },
    {
      "id": "MOVE_STRUGGLE_BUG_FAST",
      "legacy": false
    },
    {
      "id": "MOVE_INFESTATION_FAST",
      "legacy": false
    }
  ],
  "chargeMoves": [
    {
      "id": "MOVE_STRUGGLE",
      "legacy": true
    },
    {
      "id": "MOVE_SILVER_WIND",
      "legacy": false
    },
    {
      "id": "MOVE_AIR_CUTTER",
      "legacy": false
    },
    {
      "id": "MOVE_BUG_BUZZ",
      "legacy": false
    }
  ],
  "rarity": null,
  "maxCP": 1573,
  "buddyDistance": 1,
  "height": 0.99,
  "weight": 28.4,
  "family": {
    "id": "FAMILY_WURMPLE"
  },
  "_id": "POKEMON_BEAUTIFLY"
}