{
  "name": "Suicune",
  "dex": 245,
  "generation": 2,
  "types": [
    "water"
  ],
  "baseStats": {
    "stamina": 200,
    "attack": 180,
    "defense": 235
  },
  "previousEvolution": null,
  "nextEvolutions": [],
  "quickMoves": [
    "MOVE_EXTRASENSORY_FAST",
    "MOVE_SNARL_FAST"
  ],
  "chargeMoves": [
    "MOVE_HYDRO_PUMP",
    "MOVE_BUBBLE_BEAM",
    "MOVE_WATER_PULSE"
  ],
  "rarity": "legendary",
  "maxCP": 2823,
  "buddyDistance": 20,
  "height": 2.01,
  "weight": 187,
  "_id": "POKEMON_SUICUNE"
}