{
  "name": "Seel",
  "dex": 86,
  "family": "FAMILY_SEEL",
  "generation": 1,
  "types": [
    "water"
  ],
  "baseStats": {
    "stamina": 130,
    "attack": 85,
    "defense": 128
  },
  "previousEvolution": null,
  "nextEvolutions": [
    {
      "pokemon": "POKEMON_DEWGONG",
      "candy": 50
    }
  ],
  "quickMoves": {
    "MOVE_ICE_SHARD_FAST": false,
    "MOVE_LICK_FAST": false
  },
  "chargeMoves": {
    "MOVE_AURORA_BEAM": false,
    "MOVE_ICY_WIND": false,
    "MOVE_AQUA_TAIL": false
  },
  "rarity": null,
  "buddyDistance": 3,
  "height": 1.1,
  "weight": 90
}
